Supercap_analysis/__init__.py
Supercap_analysis/glob_analysis.py
Supercap_analysis/load_capacitor.py
Supercap_analysis/supercap.py
Supercap_analysis/utilities.py
Supercap_analysis/cccap/__init__.py
Supercap_analysis/cccap/cc_cap.py
Supercap_analysis/cccap/utilities.py
Supercap_analysis-14.9.2020.dist-info/LICENSE.txt
Supercap_analysis-14.9.2020.dist-info/METADATA
Supercap_analysis-14.9.2020.dist-info/WHEEL
Supercap_analysis-14.9.2020.dist-info/top_level.txt
Supercap_analysis-14.9.2020.dist-info/RECORD
