Metadata-Version: 2.1
Name: Supercap-analysis
Version: 14.9.2020
Summary: A python library for GCD analysis of supercapacitors
Home-page: https://github.com/
Author: Yuan Chen
Author-email: yuan.chen18@imperial.ac.uk
License: UNKNOWN
Platform: any
Classifier: Programming Language :: Python :: 3
Classifier: License :: OSI Approved :: MIT License
Classifier: Operating System :: OS Independent
Requires-Dist: scipy
Requires-Dist: matplotlib
Requires-Dist: numpy
Requires-Dist: pandas
Requires-Dist: IPython
Requires-Dist: datetime
